boltzmann/__init__.py
boltzmann/core.py
boltzmann-0.0.1.dist-info/LICENSE
boltzmann-0.0.1.dist-info/METADATA
boltzmann-0.0.1.dist-info/WHEEL
boltzmann-0.0.1.dist-info/top_level.txt
boltzmann-0.0.1.dist-info/RECORD
